{
  "qualifiedName": "@JunoJunHyun/festival-finder-mcp",
  "displayName": "Festival Finder",
  "description": "Discover festivals worldwide by location, date, and genre. Compare options with key details like dates, venues, and lineups to plan your trip. Save time finding events that match your interests.",
  "iconUrl": "https://icons.duckduckgo.com/ip3/github.com.ico",
  "remote": true,
  "deploymentUrl": "https://server.smithery.ai/@JunoJunHyun/festival-finder-mcp",
  "security": null,
  "tools": [
    {
      "name": "get_performance_list",
      "_meta": {
        "_fastmcp": {
          "tags": []
        }
      },
      "description": "기간별, 조건별 공연 목록을 조회합니다.",
      "inputSchema": {
        "type": "object",
        "required": [
          "stdate",
          "eddate"
        ],
        "properties": {
          "rows": {
            "type": "integer",
            "default": 10
          },
          "cpage": {
            "type": "integer",
            "default": 1
          },
          "eddate": {
            "type": "string"
          },
          "stdate": {
            "type": "string"
          },
          "shprfnm": {
            "anyOf": [
              {
                "type": "string"
              },
              {
                "type": "null"
              }
            ],
            "default": null
          },
          "prfstate": {
            "anyOf": [
              {
                "type": "string"
              },
              {
                "type": "null"
              }
            ],
            "default": null
          },
          "signgucode": {
            "anyOf": [
              {
                "type": "string"
              },
              {
                "type": "null"
              }
            ],
            "default": null
          }
        }
      }
    },
    {
      "name": "get_festival_list",
      "_meta": {
        "_fastmcp": {
          "tags": []
        }
      },
      "description": "기간별, 조건별 축제 목록을 조회합니다.",
      "inputSchema": {
        "type": "object",
        "required": [
          "stdate",
          "eddate"
        ],
        "properties": {
          "rows": {
            "type": "integer",
            "default": 10
          },
          "cpage": {
            "type": "integer",
            "default": 1
          },
          "eddate": {
            "type": "string"
          },
          "stdate": {
            "type": "string"
          },
          "shprfnm": {
            "anyOf": [
              {
                "type": "string"
              },
              {
                "type": "null"
              }
            ],
            "default": null
          },
          "signgucode": {
            "anyOf": [
              {
                "type": "string"
              },
              {
                "type": "null"
              }
            ],
            "default": null
          }
        }
      }
    },
    {
      "name": "get_performance_detail",
      "_meta": {
        "_fastmcp": {
          "tags": []
        }
      },
      "description": "특정 공연의 상세 정보를 조회합니다.",
      "inputSchema": {
        "type": "object",
        "required": [
          "performance_id"
        ],
        "properties": {
          "performance_id": {
            "type": "string"
          }
        }
      }
    }
  ],
  "connections": [
    {
      "type": "http",
      "deploymentUrl": "https://server.smithery.ai/@JunoJunHyun/festival-finder-mcp/mcp",
      "configSchema": {
        "title": "MCP Session Configuration",
        "description": "Schema for the /mcp endpoint configuration",
        "x-query-style": "dot+bracket"
      }
    }
  ]
}